grim/__init__.py
grim/mean_tester.py
grim-0.1.10.dist-info/LICENSE
grim-0.1.10.dist-info/METADATA
grim-0.1.10.dist-info/WHEEL
grim-0.1.10.dist-info/top_level.txt
grim-0.1.10.dist-info/RECORD
