Metadata-Version: 2.1
Name: grim
Version: 0.1.10
Summary: An implementation of the GRIM test, in Python
Home-page: https://github.com/phoughton/grim_test
Author: Peter Houghton
Author-email: pete@investigatingsoftware.co.uk
Classifier: Programming Language :: Python :: 3
Classifier: License :: OSI Approved :: MIT License
Classifier: Operating System :: OS Independent
Requires-Python: >=3.6
License-File: LICENSE
